{
	"timestamp_0": {
		"robots": {
			"ARMLIFT": {
				"AMR_LIFT01": {
					"name": "AMR_LIFT01",
					"pose": {
						"translation": [
							139.6189727783203,
							142.42967224121094,
							0.062001608312129974
						],
						"rotation": [
							-0.009402314200997353,
							-0.003542463295161724,
							-0.9358919858932495,
							0.35214418172836304
						]
					},
					"odometry": {
						"position": [
							0.5899351243345478,
							-7.86965220870749,
							-0.013339891563863494
						],
						"orientation": [
							-0.01981247267008238,
							0.00038889112084259915,
							-0.935720101737206,
							0.3521863226976687
						],
						"linear": [
							0.002343797590583563,
							0.0,
							0.0
						],
						"angular": [
							0.0,
							0.0,
							0.0008314793230965734
						]
					},
					"aabb": [
						123.73506202435178,
						140.76769749590665,
						-0.013942028248064184,
						124.71537457868168,
						141.70059848232506,
						0.16287419153822214
					],
					"joint_state": {
						"position": [
							-1.3842,
							4.8938,
							0.9479,
							-5.8015,
							0.9633,
							-0.971,
							0.0
						],
						"velocity": [
							0.0009,
							0.0005,
							-0.0149,
							-0.0138,
							-0.0073,
							-0.0006,
							0.0
						],
						"effort": [
							0.0,
							0.0,
							0.0,
							0.0,
							0.0,
							0.0,
							0.0
						]
					},
					"lift_state": "lift_down"
				}
			}
		},
		"objects": {
			"Rack": {
				"Rack_02": {
					"name": "Rack_02",
					"pose": {
						"translation": [
							133.05699157714844,
							143.09999084472656,
							0.19921104609966278
						],
						"rotation": [
							0.983835756778717,
							0.1790735274553299,
							-4.97384462505579e-08,
							9.080395102500916e-09
						]
					}
				}
			}
		},
		"relationships": {
			"L-Rack": [
				[
					"AMR_LIFT01",
					"none"
				]
			]
		}
	},
	"timestamp_1": {
		"robots": {
			"ARMLIFT": {
				"AMR_LIFT01": {
					"name": "AMR_LIFT01",
					"pose": {
						"translation": [
							139.61865234375,
							142.42991638183594,
							0.062004659324884415
						],
						"rotation": [
							-0.00940933357924223,
							-0.003546446096152067,
							-0.9358826875686646,
							0.35216858983039856
						]
					},
					"odometry": {
						"position": [
							0.5896129933893468,
							-7.869408078712825,
							-0.013329672887024134
						],
						"orientation": [
							-0.01981939032841376,
							0.0003851801530617642,
							-0.9357107212583515,
							0.35221085946551295
						],
						"linear": [
							-0.003479842096567154,
							0.0,
							0.0
						],
						"angular": [
							0.0,
							0.0,
							-0.0035465105902403593
						]
					},
					"aabb": [
						123.73523731414065,
						140.76769691000223,
						-0.013866949335428662,
						124.71552022907039,
						141.70064377215337,
						0.1628747072034714
					],
					"joint_state": {
						"position": [
							-1.3826,
							4.8948,
							0.961,
							-5.8031,
							0.9656,
							-0.9701,
							0.0
						],
						"velocity": [
							0.0445,
							0.0328,
							-0.1973,
							0.1281,
							-0.1736,
							0.1257,
							0.0
						],
						"effort": [
							0.0,
							0.0,
							0.0,
							0.0,
							0.0,
							0.0,
							0.0
						]
					},
					"lift_state": "lift_down"
				}
			}
		},
		"objects": {
			"Rack": {
				"Rack_02": {
					"name": "Rack_02",
					"pose": {
						"translation": [
							133.05699157714844,
							143.09999084472656,
							0.19921104609966278
						],
						"rotation": [
							0.983835756778717,
							0.1790735274553299,
							-4.97384462505579e-08,
							9.080395102500916e-09
						]
					}
				}
			}
		},
		"relationships": {
			"L-Rack": [
				[
					"AMR_LIFT01",
					"none"
				]
			]
		}
	},
	"timestamp_2": {
		"robots": {
			"ARMLIFT": {
				"AMR_LIFT01": {
					"name": "AMR_LIFT01",
					"pose": {
						"translation": [
							139.6184539794922,
							142.43031311035156,
							0.06200164556503296
						],
						"rotation": [
							-0.009407713077962399,
							-0.003544293809682131,
							-0.9359099268913269,
							0.3520961105823517
						]
					},
					"odometry": {
						"position": [
							0.5893883150033327,
							-7.869076068245125,
							-0.013329480988677717
						],
						"orientation": [
							-0.019816557850101852,
							0.00039128711374904597,
							-0.9357281661857434,
							0.35216466309957034
						],
						"linear": [
							-0.004896019585430622,
							0.0,
							0.0
						],
						"angular": [
							0.0,
							0.0,
							-0.005128694232553244
						]
					},
					"aabb": [
						123.73557944537396,
						140.76727591797604,
						-0.013805606044872942,
						124.7158516208989,
						141.7002350100507,
						0.1628696130490552
					],
					"joint_state": {
						"position": [
							-1.3811,
							4.8953,
							0.9644,
							-5.8046,
							0.9903,
							-0.9799,
							0.0
						],
						"velocity": [
							0.0148,
							-0.0081,
							0.0497,
							-0.0229,
							0.1418,
							-0.0216,
							0.0
						],
						"effort": [
							0.0,
							0.0,
							0.0,
							0.0,
							0.0,
							0.0,
							0.0
						]
					},
					"lift_state": "lift_down"
				}
			}
		},
		"objects": {
			"Rack": {
				"Rack_02": {
					"name": "Rack_02",
					"pose": {
						"translation": [
							133.05699157714844,
							143.09999084472656,
							0.19921104609966278
						],
						"rotation": [
							0.983835756778717,
							0.1790735274553299,
							-4.97384462505579e-08,
							9.080395102500916e-09
						]
					}
				}
			}
		},
		"relationships": {
			"L-Rack": [
				[
					"AMR_LIFT01",
					"none"
				]
			]
		}
	},
	"timestamp_3": {
		"robots": {
			"ARMLIFT": {
				"AMR_LIFT01": {
					"name": "AMR_LIFT01",
					"pose": {
						"translation": [
							139.6185760498047,
							142.42977905273438,
							0.06200077012181282
						],
						"rotation": [
							-0.009403149597346783,
							-0.003540970617905259,
							-0.9358264207839966,
							0.3523182272911072
						]
					},
					"odometry": {
						"position": [
							0.5895445713466051,
							-7.86955457475068,
							-0.013332076699145363
						],
						"orientation": [
							-0.01981257990686455,
							0.0003923202060001781,
							-0.9356545281876376,
							0.35236048536159587
						],
						"linear": [
							0.002307724207639694,
							0.0,
							0.0
						],
						"angular": [
							0.0,
							0.0,
							0.002772759646177292
						]
					},
					"aabb": [
						123.73522360338258,
						140.76783100440173,
						-0.013837784026486584,
						124.71551037950486,
						141.70076947169093,
						0.1628690828240164
					],
					"joint_state": {
						"position": [
							-1.3809,
							4.8957,
							0.9531,
							-5.7989,
							0.9671,
							-0.9722,
							0.0
						],
						"velocity": [
							-0.0282,
							-0.0176,
							-0.0704,
							0.0638,
							-0.1072,
							0.0348,
							0.0
						],
						"effort": [
							0.0,
							0.0,
							0.0,
							0.0,
							0.0,
							0.0,
							0.0
						]
					},
					"lift_state": "lift_down"
				}
			}
		},
		"objects": {
			"Rack": {
				"Rack_02": {
					"name": "Rack_02",
					"pose": {
						"translation": [
							133.05699157714844,
							143.09999084472656,
							0.19921104609966278
						],
						"rotation": [
							0.983835756778717,
							0.1790735274553299,
							-4.97384462505579e-08,
							9.080395102500916e-09
						]
					}
				}
			}
		},
		"relationships": {
			"L-Rack": [
				[
					"AMR_LIFT01",
					"none"
				]
			]
		}
	},
	"timestamp_4": {
		"robots": {
			"ARMLIFT": {
				"AMR_LIFT01": {
					"name": "AMR_LIFT01",
					"pose": {
						"translation": [
							139.618408203125,
							142.43006896972656,
							0.06200141832232475
						],
						"rotation": [
							-0.009394686669111252,
							-0.003543877974152565,
							-0.935680627822876,
							0.3527055084705353
						]
					},
					"odometry": {
						"position": [
							0.5893591862290707,
							-7.869408088987169,
							-0.013322396203865591
						],
						"orientation": [
							-0.019807213126879747,
							0.0003929661245000711,
							-0.935505612404446,
							0.35275596245216617
						],
						"linear": [
							0.0034418983850628138,
							0.0,
							0.0
						],
						"angular": [
							0.0,
							0.0,
							0.0027096709236502647
						]
					},
					"aabb": [
						123.735708539559,
						140.76722293899385,
						-0.013977568399887268,
						124.71572421388609,
						141.7005461030768,
						0.16287660964705203
					],
					"joint_state": {
						"position": [
							-1.3789,
							4.8964,
							0.928,
							-5.7827,
							0.9382,
							-0.9589,
							0.0
						],
						"velocity": [
							0.06,
							0.0598,
							0.0585,
							-0.0207,
							0.0515,
							-0.0239,
							0.0
						],
						"effort": [
							0.0,
							0.0,
							0.0,
							0.0,
							0.0,
							0.0,
							0.0
						]
					},
					"lift_state": "lift_down"
				}
			}
		},
		"objects": {
			"Rack": {
				"Rack_02": {
					"name": "Rack_02",
					"pose": {
						"translation": [
							133.05699157714844,
							143.09999084472656,
							0.19921104609966278
						],
						"rotation": [
							0.983835756778717,
							0.1790735274553299,
							-4.97384462505579e-08,
							9.080395102500916e-09
						]
					}
				}
			}
		},
		"relationships": {
			"L-Rack": [
				[
					"AMR_LIFT01",
					"none"
				]
			]
		}
	}
}