{
	"timestamp_0": {
		"robots": {
			"ARMLIFT": {
				"AMR_LIFT01": {
					"name": "AMR_LIFT01",
					"pose": {
						"translation": [
							139.5826873779297,
							142.56796264648438,
							0.0619998537003994
						],
						"rotation": [
							-0.009356060065329075,
							-0.003725506365299225,
							-0.9290197491645813,
							0.36989328265190125
						]
					},
					"odometry": {
						"position": [
							0.5536575144241372,
							-7.73137261556711,
							-0.012530416983804362
						],
						"orientation": [
							-0.01968950673965843,
							0.0004032991659470513,
							-0.9288483313256943,
							0.36993639732743916
						],
						"linear": [
							0.0020974064245820045,
							0.0,
							0.0
						],
						"angular": [
							0.0,
							0.0,
							0.0010394454002380371
						]
					},
					"aabb": [
						123.7825046418154,
						140.61604365517596,
						-0.012639053803958484,
						124.7508657848007,
						141.56430002353898,
						0.16314378506611013
					],
					"joint_state": {
						"position": [
							-2.3713,
							4.1877,
							1.022,
							-4.9568,
							1.0242,
							-0.042,
							0.0
						],
						"velocity": [
							-0.003,
							0.0071,
							0.0595,
							-0.0346,
							-0.0072,
							-0.0012,
							0.0
						],
						"effort": [
							0.0,
							0.0,
							0.0,
							0.0,
							0.0,
							0.0,
							0.0
						]
					},
					"lift_state": "lift_down"
				}
			}
		},
		"objects": {
			"Rack": {
				"Rack_02": {
					"name": "Rack_02",
					"pose": {
						"translation": [
							133.05699157714844,
							143.09999084472656,
							0.19921104609966278
						],
						"rotation": [
							0.983835756778717,
							0.1790735274553299,
							-4.97384462505579e-08,
							9.080395102500916e-09
						]
					}
				}
			}
		},
		"relationships": {
			"L-Rack": [
				[
					"AMR_LIFT01",
					"none"
				]
			]
		}
	},
	"timestamp_1": {
		"robots": {
			"ARMLIFT": {
				"AMR_LIFT01": {
					"name": "AMR_LIFT01",
					"pose": {
						"translation": [
							139.58200073242188,
							142.56817626953125,
							0.0620080940425396
						],
						"rotation": [
							-0.009361758828163147,
							-0.0037067094817757607,
							-0.9289529919624329,
							0.37006089091300964
						]
					},
					"odometry": {
						"position": [
							0.5529644983771477,
							-7.731157791996965,
							-0.012506766072531686
						],
						"orientation": [
							-0.019694462039391146,
							0.00042395907788119104,
							-0.9287815289083936,
							0.37010379622785045
						],
						"linear": [
							0.003105509327724576,
							0.0,
							0.0
						],
						"angular": [
							0.0,
							0.0,
							-0.0006765710422769189
						]
					},
					"aabb": [
						123.78322522290553,
						140.61576041307498,
						-0.012643077331224668,
						124.751451386088,
						141.5641702510968,
						0.16314035349760947
					],
					"joint_state": {
						"position": [
							-2.3711,
							4.1875,
							0.9961,
							-4.9413,
							1.0009,
							-0.0336,
							0.0
						],
						"velocity": [
							-0.0071,
							-0.0399,
							-0.02,
							0.0178,
							-0.025,
							0.0176,
							0.0
						],
						"effort": [
							0.0,
							0.0,
							0.0,
							0.0,
							0.0,
							0.0,
							0.0
						]
					},
					"lift_state": "lift_down"
				}
			}
		},
		"objects": {
			"Rack": {
				"Rack_02": {
					"name": "Rack_02",
					"pose": {
						"translation": [
							133.05699157714844,
							143.09999084472656,
							0.19921104609966278
						],
						"rotation": [
							0.983835756778717,
							0.1790735274553299,
							-4.97384462505579e-08,
							9.080395102500916e-09
						]
					}
				}
			}
		},
		"relationships": {
			"L-Rack": [
				[
					"AMR_LIFT01",
					"none"
				]
			]
		}
	},
	"timestamp_2": {
		"robots": {
			"ARMLIFT": {
				"AMR_LIFT01": {
					"name": "AMR_LIFT01",
					"pose": {
						"translation": [
							139.58279418945312,
							142.56719970703125,
							0.062004126608371735
						],
						"rotation": [
							-0.009355629794299603,
							-0.0037130822893232107,
							-0.9289570450782776,
							0.3700507879257202
						]
					},
					"odometry": {
						"position": [
							0.5537846102991058,
							-7.7321343171770005,
							-0.012527235084376477
						],
						"orientation": [
							-0.01969152300261783,
							0.00042127503177264553,
							-0.9287855531038359,
							0.370093856737432
						],
						"linear": [
							0.000521816429682076,
							0.0,
							0.0
						],
						"angular": [
							0.0,
							0.0,
							0.001371630933135748
						]
					},
					"aabb": [
						123.78265450770166,
						140.6165359643113,
						-0.012639027475272282,
						124.75087423288433,
						141.5649526952546,
						0.16312858636700514
					],
					"joint_state": {
						"position": [
							-2.3693,
							4.1878,
							0.9976,
							-4.9407,
							1.005,
							-0.037,
							0.0
						],
						"velocity": [
							0.0002,
							0.0001,
							-0.0064,
							-0.0001,
							0.0008,
							0.0,
							0.0
						],
						"effort": [
							0.0,
							0.0,
							0.0,
							0.0,
							0.0,
							0.0,
							0.0
						]
					},
					"lift_state": "lift_down"
				}
			}
		},
		"objects": {
			"Rack": {
				"Rack_02": {
					"name": "Rack_02",
					"pose": {
						"translation": [
							133.05699157714844,
							143.09999084472656,
							0.19921104609966278
						],
						"rotation": [
							0.983835756778717,
							0.1790735274553299,
							-4.97384462505579e-08,
							9.080395102500916e-09
						]
					}
				}
			}
		},
		"relationships": {
			"L-Rack": [
				[
					"AMR_LIFT01",
					"none"
				]
			]
		}
	},
	"timestamp_3": {
		"robots": {
			"ARMLIFT": {
				"AMR_LIFT01": {
					"name": "AMR_LIFT01",
					"pose": {
						"translation": [
							139.5832061767578,
							142.5670166015625,
							0.06200454756617546
						],
						"rotation": [
							-0.009358278475701809,
							-0.0037096149753779173,
							-0.9290555119514465,
							0.3698035180568695
						]
					},
					"odometry": {
						"position": [
							0.5541751168490952,
							-7.732310080771107,
							-0.012537322346748543
						],
						"orientation": [
							-0.019692125281075074,
							0.0004181910429016069,
							-0.9288840852725863,
							0.36984645658093934
						],
						"linear": [
							-0.0025660560932010412,
							0.0,
							0.0
						],
						"angular": [
							0.0,
							0.0,
							0.0017658780561760068
						]
					},
					"aabb": [
						123.78207604482428,
						140.61699032287154,
						-0.01264997046763143,
						124.75050900379918,
						141.56515957604736,
						0.16312893717888774
					],
					"joint_state": {
						"position": [
							-2.3683,
							4.1882,
							1.0006,
							-4.9469,
							1.02,
							-0.047,
							0.0
						],
						"velocity": [
							0.0432,
							0.0146,
							-0.047,
							0.0555,
							-0.0774,
							0.0417,
							0.0
						],
						"effort": [
							0.0,
							0.0,
							0.0,
							0.0,
							0.0,
							0.0,
							0.0
						]
					},
					"lift_state": "lift_down"
				}
			}
		},
		"objects": {
			"Rack": {
				"Rack_02": {
					"name": "Rack_02",
					"pose": {
						"translation": [
							133.05699157714844,
							143.09999084472656,
							0.19921104609966278
						],
						"rotation": [
							0.983835756778717,
							0.1790735274553299,
							-4.97384462505579e-08,
							9.080395102500916e-09
						]
					}
				}
			}
		},
		"relationships": {
			"L-Rack": [
				[
					"AMR_LIFT01",
					"none"
				]
			]
		}
	},
	"timestamp_4": {
		"robots": {
			"ARMLIFT": {
				"AMR_LIFT01": {
					"name": "AMR_LIFT01",
					"pose": {
						"translation": [
							139.58316040039062,
							142.56695556640625,
							0.06201041862368584
						],
						"rotation": [
							-0.009345867671072483,
							-0.003753550350666046,
							-0.9290351867675781,
							0.3698546290397644
						]
					},
					"odometry": {
						"position": [
							0.5541264355558846,
							-7.73236866555206,
							-0.012530323136406703
						],
						"orientation": [
							-0.019679485229778616,
							0.0003748269809918236,
							-0.9288638547746763,
							0.36989798142049185
						],
						"linear": [
							-0.0034594463650137186,
							0.0,
							0.0
						],
						"angular": [
							0.0,
							0.0,
							0.000891854811925441
						]
					},
					"aabb": [
						123.78184170431338,
						140.61718052212586,
						-0.01266085469068021,
						124.7502957744645,
						141.5653221374244,
						0.16312552312160478
					],
					"joint_state": {
						"position": [
							-2.3673,
							4.1889,
							0.9797,
							-4.9461,
							1.007,
							-0.0439,
							0.0
						],
						"velocity": [
							0.0016,
							0.0067,
							-0.0355,
							0.1404,
							-0.0497,
							0.1389,
							0.0
						],
						"effort": [
							0.0,
							0.0,
							0.0,
							0.0,
							0.0,
							0.0,
							0.0
						]
					},
					"lift_state": "lift_down"
				}
			}
		},
		"objects": {
			"Rack": {
				"Rack_02": {
					"name": "Rack_02",
					"pose": {
						"translation": [
							133.05699157714844,
							143.09999084472656,
							0.19921104609966278
						],
						"rotation": [
							0.983835756778717,
							0.1790735274553299,
							-4.97384462505579e-08,
							9.080395102500916e-09
						]
					}
				}
			}
		},
		"relationships": {
			"L-Rack": [
				[
					"AMR_LIFT01",
					"none"
				]
			]
		}
	}
}