{
	"timestamp_0": {
		"robots": {
			"ARMLIFT": {
				"AMR_LIFT01": {
					"name": "AMR_LIFT01",
					"pose": {
						"translation": [
							139.62017822265625,
							142.46168518066406,
							0.06200038641691208
						],
						"rotation": [
							-0.00941137969493866,
							-0.00359971821308136,
							-0.9339466094970703,
							0.35727062821388245
						]
					},
					"odometry": {
						"position": [
							0.5911440535088761,
							-7.837640364802683,
							-0.013367195748413243
						],
						"orientation": [
							-0.019799825745050074,
							0.0003886665049437195,
							-0.9337746115901236,
							0.3573132947268092
						],
						"linear": [
							0.0010054247686639428,
							0.0,
							0.0
						],
						"angular": [
							0.0,
							0.0,
							0.002348603680729866
						]
					},
					"aabb": [
						123.73693193701477,
						140.73183183764556,
						-0.014722623689784704,
						124.71394932868613,
						141.66929806131785,
						0.1629367291478176
					],
					"joint_state": {
						"position": [
							-1.6389,
							4.6867,
							1.037,
							-5.5974,
							1.0707,
							-0.7081,
							0.0
						],
						"velocity": [
							-0.04,
							-0.0389,
							0.0158,
							-0.1635,
							0.0422,
							0.0344,
							0.0
						],
						"effort": [
							0.0,
							0.0,
							0.0,
							0.0,
							0.0,
							0.0,
							0.0
						]
					},
					"lift_state": "lift_down"
				}
			}
		},
		"objects": {
			"Rack": {
				"Rack_02": {
					"name": "Rack_02",
					"pose": {
						"translation": [
							133.05699157714844,
							143.09999084472656,
							0.19921104609966278
						],
						"rotation": [
							0.983835756778717,
							0.1790735274553299,
							-4.97384462505579e-08,
							9.080395102500916e-09
						]
					}
				}
			}
		},
		"relationships": {
			"L-Rack": [
				[
					"AMR_LIFT01",
					"none"
				]
			]
		}
	},
	"timestamp_1": {
		"robots": {
			"ARMLIFT": {
				"AMR_LIFT01": {
					"name": "AMR_LIFT01",
					"pose": {
						"translation": [
							139.61962890625,
							142.4621124267578,
							0.06199992820620537
						],
						"rotation": [
							-0.009409990161657333,
							-0.003598162904381752,
							-0.9339037537574768,
							0.35738271474838257
						]
					},
					"odometry": {
						"position": [
							0.5906558908483368,
							-7.837279060422363,
							-0.013355572706743682
						],
						"orientation": [
							-0.01979794365601058,
							0.0003874080418534101,
							-0.9337277149080407,
							0.3574359323775537
						],
						"linear": [
							4.301368608139455e-05,
							0.0,
							0.0
						],
						"angular": [
							0.0,
							0.0,
							0.0008310814737342298
						]
					},
					"aabb": [
						123.73755283167421,
						140.7313819088993,
						-0.014732111804590999,
						124.7145025203012,
						141.6689382675989,
						0.16293580863654708
					],
					"joint_state": {
						"position": [
							-1.6379,
							4.6879,
							1.0334,
							-5.5965,
							1.0579,
							-0.7045,
							0.0
						],
						"velocity": [
							0.0074,
							0.0067,
							0.0208,
							-0.0462,
							0.0283,
							-0.0414,
							0.0
						],
						"effort": [
							0.0,
							0.0,
							0.0,
							0.0,
							0.0,
							0.0,
							0.0
						]
					},
					"lift_state": "lift_down"
				}
			}
		},
		"objects": {
			"Rack": {
				"Rack_02": {
					"name": "Rack_02",
					"pose": {
						"translation": [
							133.05699157714844,
							143.09999084472656,
							0.19921104609966278
						],
						"rotation": [
							0.983835756778717,
							0.1790735274553299,
							-4.97384462505579e-08,
							9.080395102500916e-09
						]
					}
				}
			}
		},
		"relationships": {
			"L-Rack": [
				[
					"AMR_LIFT01",
					"none"
				]
			]
		}
	},
	"timestamp_2": {
		"robots": {
			"ARMLIFT": {
				"AMR_LIFT01": {
					"name": "AMR_LIFT01",
					"pose": {
						"translation": [
							139.61952209472656,
							142.46168518066406,
							0.06200099736452103
						],
						"rotation": [
							-0.009407182224094868,
							-0.003597095375880599,
							-0.9339678883552551,
							0.35721534490585327
						]
					},
					"odometry": {
						"position": [
							0.5904899320956072,
							-7.837640398364579,
							-0.01335203269950694
						],
						"orientation": [
							-0.019795860027945374,
							0.0003906737011299093,
							-0.9337959399784789,
							0.3572577693760103
						],
						"linear": [
							0.006662767380475998,
							0.0,
							0.0
						],
						"angular": [
							0.0,
							0.0,
							0.008526504971086979
						]
					},
					"aabb": [
						123.73737470286909,
						140.73166796693155,
						-0.014742840236021909,
						124.7144089316252,
						141.66910929429713,
						0.1629340054937123
					],
					"joint_state": {
						"position": [
							-1.6387,
							4.6889,
							1.0218,
							-5.5947,
							1.046,
							-0.7018,
							0.0
						],
						"velocity": [
							-0.0103,
							0.0136,
							-0.0365,
							-0.0043,
							0.0009,
							0.0103,
							0.0
						],
						"effort": [
							0.0,
							0.0,
							0.0,
							0.0,
							0.0,
							0.0,
							0.0
						]
					},
					"lift_state": "lift_down"
				}
			}
		},
		"objects": {
			"Rack": {
				"Rack_02": {
					"name": "Rack_02",
					"pose": {
						"translation": [
							133.05699157714844,
							143.09999084472656,
							0.19921104609966278
						],
						"rotation": [
							0.983835756778717,
							0.1790735274553299,
							-4.97384462505579e-08,
							9.080395102500916e-09
						]
					}
				}
			}
		},
		"relationships": {
			"L-Rack": [
				[
					"AMR_LIFT01",
					"none"
				]
			]
		}
	},
	"timestamp_3": {
		"robots": {
			"ARMLIFT": {
				"AMR_LIFT01": {
					"name": "AMR_LIFT01",
					"pose": {
						"translation": [
							139.6195068359375,
							142.46160888671875,
							0.06200042739510536
						],
						"rotation": [
							-0.009407888166606426,
							-0.0035963731352239847,
							-0.9339756965637207,
							0.3571946620941162
						]
					},
					"odometry": {
						"position": [
							0.5904703975579084,
							-7.837718525640917,
							-0.013352149446774113
						],
						"orientation": [
							-0.019796659622664074,
							0.0003911666044393139,
							-0.9338037410286704,
							0.3572373335715797
						],
						"linear": [
							0.0005828695720992982,
							0.0,
							0.0
						],
						"angular": [
							0.0,
							0.0,
							-0.0018102992326021194
						]
					},
					"aabb": [
						123.73750674610429,
						140.73200247680722,
						-0.014722555233838816,
						124.7145767663213,
						141.66939638943836,
						0.16293529462104664
					],
					"joint_state": {
						"position": [
							-1.638,
							4.6907,
							1.0237,
							-5.6004,
							1.0445,
							-0.7057,
							0.0
						],
						"velocity": [
							0.0077,
							0.0072,
							0.2996,
							-0.1719,
							0.2545,
							-0.1741,
							0.0
						],
						"effort": [
							0.0,
							0.0,
							0.0,
							0.0,
							0.0,
							0.0,
							0.0
						]
					},
					"lift_state": "lift_down"
				}
			}
		},
		"objects": {
			"Rack": {
				"Rack_02": {
					"name": "Rack_02",
					"pose": {
						"translation": [
							133.05699157714844,
							143.09999084472656,
							0.19921104609966278
						],
						"rotation": [
							0.983835756778717,
							0.1790735274553299,
							-4.97384462505579e-08,
							9.080395102500916e-09
						]
					}
				}
			}
		},
		"relationships": {
			"L-Rack": [
				[
					"AMR_LIFT01",
					"none"
				]
			]
		}
	},
	"timestamp_4": {
		"robots": {
			"ARMLIFT": {
				"AMR_LIFT01": {
					"name": "AMR_LIFT01",
					"pose": {
						"translation": [
							139.6194610595703,
							142.4617462158203,
							0.06200077012181282
						],
						"rotation": [
							-0.009403472766280174,
							-0.0035987715236842632,
							-0.9339576363563538,
							0.35724204778671265
						]
					},
					"odometry": {
						"position": [
							0.5904215819535311,
							-7.837581808539386,
							-0.013350717405952249
						],
						"orientation": [
							-0.019792041707190258,
							0.0003892955131863612,
							-0.9337857274661647,
							0.35728467461472524
						],
						"linear": [
							0.0003933797706849873,
							0.0,
							0.0
						],
						"angular": [
							0.0,
							0.0,
							2.3737076844554394e-05
						]
					},
					"aabb": [
						123.73751122742947,
						140.7319297340637,
						-0.014731683591594406,
						124.71453546020535,
						141.6693844453566,
						0.16293411183433912
					],
					"joint_state": {
						"position": [
							-1.6374,
							4.6911,
							1.0132,
							-5.5949,
							1.0496,
							-0.7066,
							0.0
						],
						"velocity": [
							0.0002,
							0.0003,
							-0.015,
							-0.0003,
							0.022,
							0.0002,
							0.0
						],
						"effort": [
							0.0,
							0.0,
							0.0,
							0.0,
							0.0,
							0.0,
							0.0
						]
					},
					"lift_state": "lift_down"
				}
			}
		},
		"objects": {
			"Rack": {
				"Rack_02": {
					"name": "Rack_02",
					"pose": {
						"translation": [
							133.05699157714844,
							143.09999084472656,
							0.19921104609966278
						],
						"rotation": [
							0.983835756778717,
							0.1790735274553299,
							-4.97384462505579e-08,
							9.080395102500916e-09
						]
					}
				}
			}
		},
		"relationships": {
			"L-Rack": [
				[
					"AMR_LIFT01",
					"none"
				]
			]
		}
	}
}