{
	"timestamp_0": {
		"robots": {
			"ARMLIFT": {
				"AMR_LIFT01": {
					"name": "AMR_LIFT01",
					"pose": {
						"translation": [
							139.617431640625,
							142.4673309326172,
							0.06200141832232475
						],
						"rotation": [
							-0.009426299482584,
							-0.0035999321844428778,
							-0.9340285062789917,
							0.35705605149269104
						]
					},
					"odometry": {
						"position": [
							0.5884003194415558,
							-7.831995966076773,
							-0.0133049262885613
						],
						"orientation": [
							-0.0198156594128838,
							0.0003860652428478043,
							-0.9338563427480837,
							0.3570987562353508
						],
						"linear": [
							0.005132199265062809,
							0.0,
							0.0
						],
						"angular": [
							0.0,
							0.0,
							-0.0011885687708854675
						]
					},
					"aabb": [
						123.73954013990598,
						140.72635158755884,
						-0.014806998738361242,
						124.71670111112637,
						141.66363021027027,
						0.16295510649179434
					],
					"joint_state": {
						"position": [
							-1.6648,
							4.6754,
							1.1002,
							-5.5767,
							1.0713,
							-0.6805,
							0.0
						],
						"velocity": [
							0.0194,
							-0.014,
							0.0415,
							-0.0417,
							0.0875,
							-0.0407,
							0.0
						],
						"effort": [
							0.0,
							0.0,
							0.0,
							0.0,
							0.0,
							0.0,
							0.0
						]
					},
					"lift_state": "lift_down"
				}
			}
		},
		"objects": {
			"Rack": {
				"Rack_02": {
					"name": "Rack_02",
					"pose": {
						"translation": [
							133.05699157714844,
							143.09999084472656,
							0.19921104609966278
						],
						"rotation": [
							0.983835756778717,
							0.1790735274553299,
							-4.97384462505579e-08,
							9.080395102500916e-09
						]
					}
				}
			}
		},
		"relationships": {
			"L-Rack": [
				[
					"AMR_LIFT01",
					"none"
				]
			]
		}
	},
	"timestamp_1": {
		"robots": {
			"ARMLIFT": {
				"AMR_LIFT01": {
					"name": "AMR_LIFT01",
					"pose": {
						"translation": [
							139.61749267578125,
							142.46722412109375,
							0.06200256198644638
						],
						"rotation": [
							-0.009419873356819153,
							-0.003602792974561453,
							-0.9339603185653687,
							0.3572346568107605
						]
					},
					"odometry": {
						"position": [
							0.5882636022226849,
							-7.831956913446775,
							-0.013303242822777799
						],
						"orientation": [
							-0.019805124858981508,
							0.00038592780652371174,
							-0.9337914803521742,
							0.3572689173588199
						],
						"linear": [
							0.0016116687329486012,
							0.0,
							0.0
						],
						"angular": [
							0.0,
							0.0,
							-0.0006880727596580982
						]
					},
					"aabb": [
						123.73973190042766,
						140.72624514709494,
						-0.01485131270069133,
						124.7167833351827,
						141.6636676915503,
						0.16294939322527136
					],
					"joint_state": {
						"position": [
							-1.6636,
							4.6772,
							1.0856,
							-5.5686,
							1.0554,
							-0.675,
							0.0
						],
						"velocity": [
							0.0235,
							0.0239,
							-0.051,
							-0.006,
							0.125,
							-0.0823,
							0.0
						],
						"effort": [
							0.0,
							0.0,
							0.0,
							0.0,
							0.0,
							0.0,
							0.0
						]
					},
					"lift_state": "lift_down"
				}
			}
		},
		"objects": {
			"Rack": {
				"Rack_02": {
					"name": "Rack_02",
					"pose": {
						"translation": [
							133.05699157714844,
							143.09999084472656,
							0.19921104609966278
						],
						"rotation": [
							0.983835756778717,
							0.1790735274553299,
							-4.97384462505579e-08,
							9.080395102500916e-09
						]
					}
				}
			}
		},
		"relationships": {
			"L-Rack": [
				[
					"AMR_LIFT01",
					"none"
				]
			]
		}
	},
	"timestamp_2": {
		"robots": {
			"ARMLIFT": {
				"AMR_LIFT01": {
					"name": "AMR_LIFT01",
					"pose": {
						"translation": [
							139.6173553466797,
							142.46707153320312,
							0.062002141028642654
						],
						"rotation": [
							-0.0094122514128685,
							-0.0035993787460029125,
							-0.9340051412582397,
							0.357117623090744
						]
					},
					"odometry": {
						"position": [
							0.5883222433066329,
							-7.832259641232442,
							-0.013302491031691671
						],
						"orientation": [
							-0.019801348974653285,
							0.0003873038230828159,
							-0.933833134452972,
							0.35716023514981365
						],
						"linear": [
							0.003676601918414235,
							0.0,
							0.0
						],
						"angular": [
							0.0,
							0.0,
							0.0028121168725192547
						]
					},
					"aabb": [
						123.73965873772515,
						140.72656876481767,
						-0.014867080368237933,
						124.71677657515431,
						141.66390035617758,
						0.16294920151663053
					],
					"joint_state": {
						"position": [
							-1.6634,
							4.6775,
							1.0581,
							-5.5617,
							1.0337,
							-0.6677,
							0.0
						],
						"velocity": [
							0.0103,
							-0.0111,
							0.0492,
							-0.0366,
							0.0684,
							-0.0235,
							0.0
						],
						"effort": [
							0.0,
							0.0,
							0.0,
							0.0,
							0.0,
							0.0,
							0.0
						]
					},
					"lift_state": "lift_down"
				}
			}
		},
		"objects": {
			"Rack": {
				"Rack_02": {
					"name": "Rack_02",
					"pose": {
						"translation": [
							133.05699157714844,
							143.09999084472656,
							0.19921104609966278
						],
						"rotation": [
							0.983835756778717,
							0.1790735274553299,
							-4.97384462505579e-08,
							9.080395102500916e-09
						]
					}
				}
			}
		},
		"relationships": {
			"L-Rack": [
				[
					"AMR_LIFT01",
					"none"
				]
			]
		}
	},
	"timestamp_3": {
		"robots": {
			"ARMLIFT": {
				"AMR_LIFT01": {
					"name": "AMR_LIFT01",
					"pose": {
						"translation": [
							139.61790466308594,
							142.46676635742188,
							0.06199943274259567
						],
						"rotation": [
							-0.009414623491466045,
							-0.0035982001572847366,
							-0.9340397119522095,
							0.3570270240306854
						]
					},
					"odometry": {
						"position": [
							0.5888689384452023,
							-7.832562352509529,
							-0.013317378639640455
						],
						"orientation": [
							-0.019804109739504597,
							0.00038747475474324014,
							-0.9338676801441622,
							0.35706974540403336
						],
						"linear": [
							0.0008508897153660655,
							0.0,
							0.0
						],
						"angular": [
							0.0,
							0.0,
							0.001101193716749549
						]
					},
					"aabb": [
						123.73911035227026,
						140.72698752351312,
						-0.014844121528902212,
						124.71626075117086,
						141.66427580777304,
						0.16294766192144836
					],
					"joint_state": {
						"position": [
							-1.6617,
							4.6779,
							1.0621,
							-5.5703,
							1.0466,
							-0.6736,
							0.0
						],
						"velocity": [
							-0.011,
							0.0002,
							-0.0064,
							-0.0211,
							-0.0963,
							0.1202,
							0.0
						],
						"effort": [
							0.0,
							0.0,
							0.0,
							0.0,
							0.0,
							0.0,
							0.0
						]
					},
					"lift_state": "lift_down"
				}
			}
		},
		"objects": {
			"Rack": {
				"Rack_02": {
					"name": "Rack_02",
					"pose": {
						"translation": [
							133.05699157714844,
							143.09999084472656,
							0.19921104609966278
						],
						"rotation": [
							0.983835756778717,
							0.1790735274553299,
							-4.97384462505579e-08,
							9.080395102500916e-09
						]
					}
				}
			}
		},
		"relationships": {
			"L-Rack": [
				[
					"AMR_LIFT01",
					"none"
				]
			]
		}
	},
	"timestamp_4": {
		"robots": {
			"ARMLIFT": {
				"AMR_LIFT01": {
					"name": "AMR_LIFT01",
					"pose": {
						"translation": [
							139.6181640625,
							142.46633911132812,
							0.06200168654322624
						],
						"rotation": [
							-0.00941399298608303,
							-0.003600947791710496,
							-0.9340356588363647,
							0.3570377230644226
						]
					},
					"odometry": {
						"position": [
							0.5891326183192906,
							-7.8329920223539515,
							-0.013320978906919169
						],
						"orientation": [
							-0.019803431739201748,
							0.0003848460598529337,
							-0.9338636313282855,
							0.3570803747998608
						],
						"linear": [
							0.006361359730362892,
							0.0,
							0.0
						],
						"angular": [
							0.0,
							0.0,
							-0.002104255836457014
						]
					},
					"aabb": [
						123.73891876354003,
						140.72705854595768,
						-0.01485430778609647,
						124.71605506496057,
						141.6643661064129,
						0.16294820557767387
					],
					"joint_state": {
						"position": [
							-1.6615,
							4.6771,
							1.0576,
							-5.569,
							1.0422,
							-0.6725,
							0.0
						],
						"velocity": [
							0.003,
							0.0025,
							0.0359,
							-0.1911,
							0.0547,
							-0.2062,
							0.0
						],
						"effort": [
							0.0,
							0.0,
							0.0,
							0.0,
							0.0,
							0.0,
							0.0
						]
					},
					"lift_state": "lift_down"
				}
			}
		},
		"objects": {
			"Rack": {
				"Rack_02": {
					"name": "Rack_02",
					"pose": {
						"translation": [
							133.05699157714844,
							143.09999084472656,
							0.19921104609966278
						],
						"rotation": [
							0.983835756778717,
							0.1790735274553299,
							-4.97384462505579e-08,
							9.080395102500916e-09
						]
					}
				}
			}
		},
		"relationships": {
			"L-Rack": [
				[
					"AMR_LIFT01",
					"none"
				]
			]
		}
	}
}