{
	"timestamp_0": {
		"robots": {
			"ARMLIFT": {
				"AMR_LIFT01": {
					"name": "AMR_LIFT01",
					"pose": {
						"translation": [
							139.5733642578125,
							142.590576171875,
							0.06200370565056801
						],
						"rotation": [
							-0.009300120174884796,
							-0.003718918887898326,
							-0.9289145469665527,
							0.3701588213443756
						]
					},
					"odometry": {
						"position": [
							0.5444399746944337,
							-7.70882422265002,
							-0.012319655733357674
						],
						"orientation": [
							-0.01963646815790568,
							0.0004212858506249295,
							-0.9287466417329434,
							0.37019441798370667
						],
						"linear": [
							0.0020039333030581474,
							0.0,
							0.0
						],
						"angular": [
							0.0,
							0.0,
							-0.00015813650679774582
						]
					},
					"aabb": [
						123.79198303159204,
						140.59332135850633,
						-0.01191765167530566,
						124.76016783377312,
						141.54175979342617,
						0.16316713527652177
					],
					"joint_state": {
						"position": [
							-2.4774,
							4.095,
							0.8387,
							-4.7701,
							0.8551,
							0.1689,
							0.0
						],
						"velocity": [
							0.0092,
							0.0038,
							-0.0365,
							0.0221,
							-0.0486,
							0.0233,
							0.0
						],
						"effort": [
							0.0,
							0.0,
							0.0,
							0.0,
							0.0,
							0.0,
							0.0
						]
					},
					"lift_state": "lift_down"
				}
			}
		},
		"objects": {
			"Rack": {
				"Rack_02": {
					"name": "Rack_02",
					"pose": {
						"translation": [
							133.05699157714844,
							143.09999084472656,
							0.19921104609966278
						],
						"rotation": [
							0.983835756778717,
							0.1790735274553299,
							-4.97384462505579e-08,
							9.080395102500916e-09
						]
					}
				}
			}
		},
		"relationships": {
			"L-Rack": [
				[
					"AMR_LIFT01",
					"none"
				]
			]
		}
	},
	"timestamp_1": {
		"robots": {
			"ARMLIFT": {
				"AMR_LIFT01": {
					"name": "AMR_LIFT01",
					"pose": {
						"translation": [
							139.5734405517578,
							142.59027099609375,
							0.06200416386127472
						],
						"rotation": [
							-0.009293798357248306,
							-0.003718928899616003,
							-0.9287479519844055,
							0.3705766797065735
						]
					},
					"odometry": {
						"position": [
							0.5444009190365658,
							-7.709058601530873,
							-0.01231947293544156
						],
						"orientation": [
							-0.01962421999797981,
							0.0004174801269653157,
							-0.9285772321353734,
							0.3706198047320511
						],
						"linear": [
							-0.0017183722229674459,
							0.0,
							0.0
						],
						"angular": [
							0.0,
							0.0,
							-0.0019857557490468025
						]
					},
					"aabb": [
						123.79219994070833,
						140.59348403947823,
						-0.011918806456439586,
						124.76017087894702,
						141.54216800326512,
						0.16315533283304207
					],
					"joint_state": {
						"position": [
							-2.4759,
							4.0955,
							0.8206,
							-4.7615,
							0.8274,
							0.1693,
							0.0
						],
						"velocity": [
							-0.0123,
							0.0058,
							0.0143,
							0.0137,
							-0.0256,
							0.001,
							0.0
						],
						"effort": [
							0.0,
							0.0,
							0.0,
							0.0,
							0.0,
							0.0,
							0.0
						]
					},
					"lift_state": "lift_down"
				}
			}
		},
		"objects": {
			"Rack": {
				"Rack_02": {
					"name": "Rack_02",
					"pose": {
						"translation": [
							133.05699157714844,
							143.09999084472656,
							0.19921104609966278
						],
						"rotation": [
							0.983835756778717,
							0.1790735274553299,
							-4.97384462505579e-08,
							9.080395102500916e-09
						]
					}
				}
			}
		},
		"relationships": {
			"L-Rack": [
				[
					"AMR_LIFT01",
					"none"
				]
			]
		}
	},
	"timestamp_2": {
		"robots": {
			"ARMLIFT": {
				"AMR_LIFT01": {
					"name": "AMR_LIFT01",
					"pose": {
						"translation": [
							139.5740966796875,
							142.58941650390625,
							0.062010038644075394
						],
						"rotation": [
							-0.009303081780672073,
							-0.0037089320831000805,
							-0.9286625385284424,
							0.3707907497882843
						]
					},
					"odometry": {
						"position": [
							0.5450649919025247,
							-7.709908165764541,
							-0.012328424643629692
						],
						"orientation": [
							-0.01963254333288987,
							0.00042985659283770606,
							-0.9284917249024977,
							0.37083351419899524
						],
						"linear": [
							0.004395151045173407,
							0.0,
							0.0
						],
						"angular": [
							0.0,
							0.0,
							0.0066349320113658905
						]
					},
					"aabb": [
						123.7918247975982,
						140.5937580509277,
						-0.011944643645799327,
						124.75955786964809,
						141.54271517069003,
						0.16316064473229994
					],
					"joint_state": {
						"position": [
							-2.4746,
							4.0953,
							0.8181,
							-4.7582,
							0.8181,
							0.1651,
							0.0
						],
						"velocity": [
							0.0055,
							-0.0395,
							-0.177,
							0.0736,
							0.3343,
							-0.1894,
							0.0
						],
						"effort": [
							0.0,
							0.0,
							0.0,
							0.0,
							0.0,
							0.0,
							0.0
						]
					},
					"lift_state": "lift_down"
				}
			}
		},
		"objects": {
			"Rack": {
				"Rack_02": {
					"name": "Rack_02",
					"pose": {
						"translation": [
							133.05699157714844,
							143.09999084472656,
							0.19921104609966278
						],
						"rotation": [
							0.983835756778717,
							0.1790735274553299,
							-4.97384462505579e-08,
							9.080395102500916e-09
						]
					}
				}
			}
		},
		"relationships": {
			"L-Rack": [
				[
					"AMR_LIFT01",
					"none"
				]
			]
		}
	},
	"timestamp_3": {
		"robots": {
			"ARMLIFT": {
				"AMR_LIFT01": {
					"name": "AMR_LIFT01",
					"pose": {
						"translation": [
							139.5742950439453,
							142.58935546875,
							0.06200607120990753
						],
						"rotation": [
							-0.009300557896494865,
							-0.003694445826113224,
							-0.9286043047904968,
							0.3709368407726288
						]
					},
					"odometry": {
						"position": [
							0.5452601715937647,
							-7.709976522708823,
							-0.012336727029979018
						],
						"orientation": [
							-0.01962937043071329,
							0.00044596734632432726,
							-0.9284334736525507,
							0.3709794791239517
						],
						"linear": [
							-0.006521542090922594,
							0.0,
							0.0
						],
						"angular": [
							0.0,
							0.0,
							0.005617226008325815
						]
					},
					"aabb": [
						123.7916549730138,
						140.5940635658579,
						-0.011947748996464912,
						124.75928665399456,
						141.54313826391027,
						0.16316114101646317
					],
					"joint_state": {
						"position": [
							-2.4733,
							4.0958,
							0.8129,
							-4.7543,
							0.8103,
							0.1703,
							0.0
						],
						"velocity": [
							0.0879,
							0.046,
							-0.1487,
							0.087,
							-0.2179,
							0.0695,
							0.0
						],
						"effort": [
							0.0,
							0.0,
							0.0,
							0.0,
							0.0,
							0.0,
							0.0
						]
					},
					"lift_state": "lift_down"
				}
			}
		},
		"objects": {
			"Rack": {
				"Rack_02": {
					"name": "Rack_02",
					"pose": {
						"translation": [
							133.05699157714844,
							143.09999084472656,
							0.19921104609966278
						],
						"rotation": [
							0.983835756778717,
							0.1790735274553299,
							-4.97384462505579e-08,
							9.080395102500916e-09
						]
					}
				}
			}
		},
		"relationships": {
			"L-Rack": [
				[
					"AMR_LIFT01",
					"none"
				]
			]
		}
	},
	"timestamp_4": {
		"robots": {
			"ARMLIFT": {
				"AMR_LIFT01": {
					"name": "AMR_LIFT01",
					"pose": {
						"translation": [
							139.57395935058594,
							142.5895233154297,
							0.06200626119971275
						],
						"rotation": [
							-0.009284872561693192,
							-0.003732137382030487,
							-0.928510844707489,
							0.37117061018943787
						]
					},
					"odometry": {
						"position": [
							0.5449282164730677,
							-7.7098007584692505,
							-0.01232919286313655
						],
						"orientation": [
							-0.01961264430889166,
							0.00041087914161655,
							-0.9283402100823168,
							0.3712137251043712
						],
						"linear": [
							0.0029543559066951275,
							0.0,
							0.0
						],
						"angular": [
							0.0,
							0.0,
							0.005281268153339624
						]
					},
					"aabb": [
						123.79200286309693,
						140.59359171946645,
						-0.011968769774053725,
						124.75943831415415,
						141.54288835731504,
						0.16316632400804526
					],
					"joint_state": {
						"position": [
							-2.4731,
							4.0953,
							0.8018,
							-4.7507,
							0.8135,
							0.1682,
							0.0
						],
						"velocity": [
							-0.028,
							-0.029,
							0.0324,
							0.0416,
							0.2935,
							-0.1267,
							0.0
						],
						"effort": [
							0.0,
							0.0,
							0.0,
							0.0,
							0.0,
							0.0,
							0.0
						]
					},
					"lift_state": "lift_down"
				}
			}
		},
		"objects": {
			"Rack": {
				"Rack_02": {
					"name": "Rack_02",
					"pose": {
						"translation": [
							133.05699157714844,
							143.09999084472656,
							0.19921104609966278
						],
						"rotation": [
							0.983835756778717,
							0.1790735274553299,
							-4.97384462505579e-08,
							9.080395102500916e-09
						]
					}
				}
			}
		},
		"relationships": {
			"L-Rack": [
				[
					"AMR_LIFT01",
					"none"
				]
			]
		}
	}
}