{
	"timestamp_0": {
		"robots": {
			"ARMLIFT": {
				"AMR_LIFT01": {
					"name": "AMR_LIFT01",
					"pose": {
						"translation": [
							139.61419677734375,
							142.47911071777344,
							0.062002599239349365
						],
						"rotation": [
							-0.009424158371984959,
							-0.0036417555529624224,
							-0.9329310059547424,
							0.3599136471748352
						]
					},
					"odometry": {
						"position": [
							0.5851583426381017,
							-7.820209003241076,
							-0.013231255136157012
						],
						"orientation": [
							-0.019801265064543987,
							0.0003760317947404811,
							-0.9327588169393235,
							0.35995660561224135
						],
						"linear": [
							0.004477251786738634,
							0.0,
							0.0
						],
						"angular": [
							0.0,
							0.0,
							-0.005013637710362673
						]
					},
					"aabb": [
						123.7447527039543,
						140.71205673906016,
						-0.014942115675914225,
						124.71992764453995,
						141.6519632130006,
						0.16297613334930838
					],
					"joint_state": {
						"position": [
							-1.7765,
							4.6049,
							1.1122,
							-5.5189,
							1.1071,
							-0.6769,
							0.0
						],
						"velocity": [
							-0.0435,
							-0.0298,
							0.1706,
							-0.1408,
							0.1324,
							-0.0687,
							0.0
						],
						"effort": [
							0.0,
							0.0,
							0.0,
							0.0,
							0.0,
							0.0,
							0.0
						]
					},
					"lift_state": "lift_down"
				}
			}
		},
		"objects": {
			"Rack": {
				"Rack_02": {
					"name": "Rack_02",
					"pose": {
						"translation": [
							133.05699157714844,
							143.09999084472656,
							0.19921104609966278
						],
						"rotation": [
							0.983835756778717,
							0.1790735274553299,
							-4.97384462505579e-08,
							9.080395102500916e-09
						]
					}
				}
			}
		},
		"relationships": {
			"L-Rack": [
				[
					"AMR_LIFT01",
					"none"
				]
			]
		}
	},
	"timestamp_1": {
		"robots": {
			"ARMLIFT": {
				"AMR_LIFT01": {
					"name": "AMR_LIFT01",
					"pose": {
						"translation": [
							139.61387634277344,
							142.4795379638672,
							0.062002141028642654
						],
						"rotation": [
							-0.009414791129529476,
							-0.0036444070283323526,
							-0.9327521324157715,
							0.3603774309158325
						]
					},
					"odometry": {
						"position": [
							0.5848458875864895,
							-7.819789098056113,
							-0.013224756401540246
						],
						"orientation": [
							-0.01978989486992991,
							0.0003785390493931299,
							-0.9325800438543047,
							0.36042014174283954
						],
						"linear": [
							-0.004472245462238789,
							0.0,
							0.0
						],
						"angular": [
							0.0,
							0.0,
							0.002995169721543789
						]
					},
					"aabb": [
						123.74510083587282,
						140.7117078383225,
						-0.014942398798792958,
						124.720062022149,
						141.6518890827868,
						0.16297405638364443
					],
					"joint_state": {
						"position": [
							-1.7739,
							4.6052,
							1.0953,
							-5.5086,
							1.0868,
							-0.671,
							0.0
						],
						"velocity": [
							0.0269,
							0.0161,
							0.1041,
							-0.0469,
							0.1027,
							-0.0341,
							0.0
						],
						"effort": [
							0.0,
							0.0,
							0.0,
							0.0,
							0.0,
							0.0,
							0.0
						]
					},
					"lift_state": "lift_down"
				}
			}
		},
		"objects": {
			"Rack": {
				"Rack_02": {
					"name": "Rack_02",
					"pose": {
						"translation": [
							133.05699157714844,
							143.09999084472656,
							0.19921104609966278
						],
						"rotation": [
							0.983835756778717,
							0.1790735274553299,
							-4.97384462505579e-08,
							9.080395102500916e-09
						]
					}
				}
			}
		},
		"relationships": {
			"L-Rack": [
				[
					"AMR_LIFT01",
					"none"
				]
			]
		}
	},
	"timestamp_2": {
		"robots": {
			"ARMLIFT": {
				"AMR_LIFT01": {
					"name": "AMR_LIFT01",
					"pose": {
						"translation": [
							139.61424255371094,
							142.47901916503906,
							0.06200023368000984
						],
						"rotation": [
							-0.009419562295079231,
							-0.0036382577382028103,
							-0.9328169822692871,
							0.3602091073989868
						]
					},
					"odometry": {
						"position": [
							0.5852071098789675,
							-7.820306661873252,
							-0.013234766441760795
						],
						"orientation": [
							-0.019795399447361008,
							0.0003828167617893026,
							-0.9326448470206512,
							0.36025211302346666
						],
						"linear": [
							0.0005655374261550605,
							0.0,
							0.0
						],
						"angular": [
							0.0,
							0.0,
							0.0024613093119114637
						]
					},
					"aabb": [
						123.74505780299056,
						140.71187553029472,
						-0.014945620352284878,
						124.72011668771898,
						141.65193259563412,
						0.16297906225294717
					],
					"joint_state": {
						"position": [
							-1.7738,
							4.6055,
							1.1001,
							-5.5057,
							1.0982,
							-0.6717,
							0.0
						],
						"velocity": [
							-0.0077,
							-0.0074,
							-0.049,
							0.0495,
							-0.0681,
							0.0411,
							0.0
						],
						"effort": [
							0.0,
							0.0,
							0.0,
							0.0,
							0.0,
							0.0,
							0.0
						]
					},
					"lift_state": "lift_down"
				}
			}
		},
		"objects": {
			"Rack": {
				"Rack_02": {
					"name": "Rack_02",
					"pose": {
						"translation": [
							133.05699157714844,
							143.09999084472656,
							0.19921104609966278
						],
						"rotation": [
							0.983835756778717,
							0.1790735274553299,
							-4.97384462505579e-08,
							9.080395102500916e-09
						]
					}
				}
			}
		},
		"relationships": {
			"L-Rack": [
				[
					"AMR_LIFT01",
					"none"
				]
			]
		}
	},
	"timestamp_3": {
		"robots": {
			"ARMLIFT": {
				"AMR_LIFT01": {
					"name": "AMR_LIFT01",
					"pose": {
						"translation": [
							139.6142120361328,
							142.47885131835938,
							0.062001533806324005
						],
						"rotation": [
							-0.009411841630935669,
							-0.0036382346879690886,
							-0.9329109787940979,
							0.3599660098552704
						]
					},
					"odometry": {
						"position": [
							0.5851680965049684,
							-7.8204824428648445,
							-0.013232544451136443
						],
						"orientation": [
							-0.019788722772566193,
							0.0003801349561218223,
							-0.9327389302083441,
							0.36000881936730333
						],
						"linear": [
							-0.002774876309558749,
							0.0,
							0.0
						],
						"angular": [
							0.0,
							0.0,
							0.0016463164938613772
						]
					},
					"aabb": [
						123.74436766934073,
						140.71286625086682,
						-0.014942969672324093,
						124.71960899803202,
						141.65268474248558,
						0.16297850618745607
					],
					"joint_state": {
						"position": [
							-1.7739,
							4.6072,
							1.0702,
							-5.4925,
							1.0773,
							-0.6566,
							0.0
						],
						"velocity": [
							0.007,
							0.0126,
							-0.0479,
							0.0651,
							-0.0829,
							0.06,
							0.0
						],
						"effort": [
							0.0,
							0.0,
							0.0,
							0.0,
							0.0,
							0.0,
							0.0
						]
					},
					"lift_state": "lift_down"
				}
			}
		},
		"objects": {
			"Rack": {
				"Rack_02": {
					"name": "Rack_02",
					"pose": {
						"translation": [
							133.05699157714844,
							143.09999084472656,
							0.19921104609966278
						],
						"rotation": [
							0.983835756778717,
							0.1790735274553299,
							-4.97384462505579e-08,
							9.080395102500916e-09
						]
					}
				}
			}
		},
		"relationships": {
			"L-Rack": [
				[
					"AMR_LIFT01",
					"none"
				]
			]
		}
	},
	"timestamp_4": {
		"robots": {
			"ARMLIFT": {
				"AMR_LIFT01": {
					"name": "AMR_LIFT01",
					"pose": {
						"translation": [
							139.6138458251953,
							142.4789581298828,
							0.062006108462810516
						],
						"rotation": [
							-0.009410996921360493,
							-0.003644057549536228,
							-0.932801365852356,
							0.360249787569046
						]
					},
					"odometry": {
						"position": [
							0.584806953277319,
							-7.820375031005806,
							-0.013219961542091803
						],
						"orientation": [
							-0.019786657932302196,
							0.00037746968654231666,
							-0.9326293201152871,
							0.360292793358129
						],
						"linear": [
							-0.0018996581202372909,
							0.0,
							0.0
						],
						"angular": [
							0.0,
							0.0,
							0.0021257863845676184
						]
					},
					"aabb": [
						123.74496257807851,
						140.71253081800532,
						-0.014937740921838931,
						124.72007014984194,
						141.65251978389105,
						0.16297304419889694
					],
					"joint_state": {
						"position": [
							-1.7735,
							4.607,
							1.0611,
							-5.4887,
							1.0659,
							-0.6492,
							0.0
						],
						"velocity": [
							0.0043,
							-0.0009,
							-0.0091,
							0.0004,
							-0.0151,
							-0.0012,
							0.0
						],
						"effort": [
							0.0,
							0.0,
							0.0,
							0.0,
							0.0,
							0.0,
							0.0
						]
					},
					"lift_state": "lift_down"
				}
			}
		},
		"objects": {
			"Rack": {
				"Rack_02": {
					"name": "Rack_02",
					"pose": {
						"translation": [
							133.05699157714844,
							143.09999084472656,
							0.19921104609966278
						],
						"rotation": [
							0.983835756778717,
							0.1790735274553299,
							-4.97384462505579e-08,
							9.080395102500916e-09
						]
					}
				}
			}
		},
		"relationships": {
			"L-Rack": [
				[
					"AMR_LIFT01",
					"none"
				]
			]
		}
	}
}