{
	"timestamp_0": {
		"robots": {
			"ARMLIFT": {
				"AMR_LIFT01": {
					"name": "AMR_LIFT01",
					"pose": {
						"translation": [
							139.60707092285156,
							142.51206970214844,
							0.06201209872961044
						],
						"rotation": [
							-0.009424006566405296,
							-0.0037516539450734854,
							-0.9296556115150452,
							0.36829015612602234
						]
					},
					"odometry": {
						"position": [
							0.5780394463034683,
							-7.787260078741386,
							-0.013062433956104694
						],
						"orientation": [
							-0.019764550620719624,
							0.0003593191930627056,
							-0.9294834149177084,
							0.36833383610713
						],
						"linear": [
							0.0001382002083119005,
							0.0,
							0.0
						],
						"angular": [
							0.0,
							0.0,
							0.004059043247252703
						]
					},
					"aabb": [
						123.75728279920858,
						140.67332342800782,
						-0.013219643954524574,
						124.72688320280973,
						141.6201481928444,
						0.16304289708650796
					],
					"joint_state": {
						"position": [
							-2.0373,
							4.4148,
							1.1778,
							-5.2686,
							1.1883,
							-0.4298,
							0.0
						],
						"velocity": [
							-0.0174,
							0.0154,
							-0.0301,
							0.0557,
							-0.0709,
							0.0412,
							0.0
						],
						"effort": [
							0.0,
							0.0,
							0.0,
							0.0,
							0.0,
							0.0,
							0.0
						]
					},
					"lift_state": "lift_down"
				}
			}
		},
		"objects": {
			"Rack": {
				"Rack_02": {
					"name": "Rack_02",
					"pose": {
						"translation": [
							133.05699157714844,
							143.09999084472656,
							0.19921104609966278
						],
						"rotation": [
							0.983835756778717,
							0.1790735274553299,
							-4.97384462505579e-08,
							9.080395102500916e-09
						]
					}
				}
			}
		},
		"relationships": {
			"L-Rack": [
				[
					"AMR_LIFT01",
					"none"
				]
			]
		}
	},
	"timestamp_1": {
		"robots": {
			"ARMLIFT": {
				"AMR_LIFT01": {
					"name": "AMR_LIFT01",
					"pose": {
						"translation": [
							139.606689453125,
							142.5123748779297,
							0.06200267747044563
						],
						"rotation": [
							-0.009425328113138676,
							-0.003728090086951852,
							-0.9296250343322754,
							0.3683674931526184
						]
					},
					"odometry": {
						"position": [
							0.5776486918412722,
							-7.786947617479813,
							-0.01306315660161714
						],
						"orientation": [
							-0.019765531314119848,
							0.0003837418356163077,
							-0.9294528461184507,
							0.36841088930212956
						],
						"linear": [
							-0.0020968816243112087,
							0.0,
							0.0
						],
						"angular": [
							0.0,
							0.0,
							0.002514110179618001
						]
					},
					"aabb": [
						123.75756245085937,
						140.67248775715876,
						-0.013270677793607437,
						124.72699886203345,
						141.61950538336927,
						0.16304394083911414
					],
					"joint_state": {
						"position": [
							-2.0366,
							4.4153,
							1.1911,
							-5.2775,
							1.1914,
							-0.4325,
							0.0
						],
						"velocity": [
							0.0346,
							0.0032,
							0.0005,
							0.0378,
							-0.0177,
							0.0258,
							0.0
						],
						"effort": [
							0.0,
							0.0,
							0.0,
							0.0,
							0.0,
							0.0,
							0.0
						]
					},
					"lift_state": "lift_down"
				}
			}
		},
		"objects": {
			"Rack": {
				"Rack_02": {
					"name": "Rack_02",
					"pose": {
						"translation": [
							133.05699157714844,
							143.09999084472656,
							0.19921104609966278
						],
						"rotation": [
							0.983835756778717,
							0.1790735274553299,
							-4.97384462505579e-08,
							9.080395102500916e-09
						]
					}
				}
			}
		},
		"relationships": {
			"L-Rack": [
				[
					"AMR_LIFT01",
					"none"
				]
			]
		}
	},
	"timestamp_2": {
		"robots": {
			"ARMLIFT": {
				"AMR_LIFT01": {
					"name": "AMR_LIFT01",
					"pose": {
						"translation": [
							139.60585021972656,
							142.5133514404297,
							0.062003400176763535
						],
						"rotation": [
							-0.009426403790712357,
							-0.0037276658695191145,
							-0.9296281337738037,
							0.36835989356040955
						]
					},
					"odometry": {
						"position": [
							0.5768187841250834,
							-7.785980861398758,
							-0.013043957407776734
						],
						"orientation": [
							-0.01976663510939573,
							0.00038408051203900627,
							-0.929455934097508,
							0.3684030390612182
						],
						"linear": [
							0.0008523130090907216,
							0.0,
							0.0
						],
						"angular": [
							0.0,
							0.0,
							0.002551731187850237
						]
					},
					"aabb": [
						123.75809181298779,
						140.67202093187194,
						-0.013247068498479486,
						124.72756876307498,
						141.61899213501,
						0.1630572607947616
					],
					"joint_state": {
						"position": [
							-2.036,
							4.4151,
							1.1914,
							-5.2761,
							1.193,
							-0.4309,
							0.0
						],
						"velocity": [
							0.0,
							0.0007,
							-0.0348,
							0.0122,
							-0.1376,
							0.0956,
							0.0
						],
						"effort": [
							0.0,
							0.0,
							0.0,
							0.0,
							0.0,
							0.0,
							0.0
						]
					},
					"lift_state": "lift_down"
				}
			}
		},
		"objects": {
			"Rack": {
				"Rack_02": {
					"name": "Rack_02",
					"pose": {
						"translation": [
							133.05699157714844,
							143.09999084472656,
							0.19921104609966278
						],
						"rotation": [
							0.983835756778717,
							0.1790735274553299,
							-4.97384462505579e-08,
							9.080395102500916e-09
						]
					}
				}
			}
		},
		"relationships": {
			"L-Rack": [
				[
					"AMR_LIFT01",
					"none"
				]
			]
		}
	},
	"timestamp_3": {
		"robots": {
			"ARMLIFT": {
				"AMR_LIFT01": {
					"name": "AMR_LIFT01",
					"pose": {
						"translation": [
							139.60604858398438,
							142.5128631591797,
							0.06200283020734787
						],
						"rotation": [
							-0.009424224495887756,
							-0.0037295082584023476,
							-0.9295587539672852,
							0.36853498220443726
						]
					},
					"odometry": {
						"position": [
							0.5770042983461383,
							-7.786469134853477,
							-0.013048654194865892
						],
						"orientation": [
							-0.019763681349800888,
							0.00038418594094791257,
							-0.9293865763656245,
							0.36857813414803914
						],
						"linear": [
							-0.0022716112434864044,
							0.0,
							0.0
						],
						"angular": [
							0.0,
							0.0,
							-0.001689123921096325
						]
					},
					"aabb": [
						123.75833749652489,
						140.6719895773533,
						-0.013290458130007381,
						124.72771772927165,
						141.61907332174658,
						0.16304507011354027
					],
					"joint_state": {
						"position": [
							-2.0353,
							4.4161,
							1.1943,
							-5.2702,
							1.185,
							-0.4198,
							0.0
						],
						"velocity": [
							0.0026,
							-0.0044,
							0.0383,
							0.0018,
							0.1023,
							-0.0459,
							0.0
						],
						"effort": [
							0.0,
							0.0,
							0.0,
							0.0,
							0.0,
							0.0,
							0.0
						]
					},
					"lift_state": "lift_down"
				}
			}
		},
		"objects": {
			"Rack": {
				"Rack_02": {
					"name": "Rack_02",
					"pose": {
						"translation": [
							133.05699157714844,
							143.09999084472656,
							0.19921104609966278
						],
						"rotation": [
							0.983835756778717,
							0.1790735274553299,
							-4.97384462505579e-08,
							9.080395102500916e-09
						]
					}
				}
			}
		},
		"relationships": {
			"L-Rack": [
				[
					"AMR_LIFT01",
					"none"
				]
			]
		}
	},
	"timestamp_4": {
		"robots": {
			"ARMLIFT": {
				"AMR_LIFT01": {
					"name": "AMR_LIFT01",
					"pose": {
						"translation": [
							139.60621643066406,
							142.5128173828125,
							0.062002599239349365
						],
						"rotation": [
							-0.009423281066119671,
							-0.0037297948729246855,
							-0.9295563697814941,
							0.36854106187820435
						]
					},
					"odometry": {
						"position": [
							0.5770825695727035,
							-7.786576538605302,
							-0.013043211484268347
						],
						"orientation": [
							-0.01976915828907628,
							0.00037788374654922486,
							-0.9293940801740589,
							0.3685589251691384
						],
						"linear": [
							-0.008835074491798878,
							0.0,
							0.0
						],
						"angular": [
							0.0,
							0.0,
							0.0030466951429843903
						]
					},
					"aabb": [
						123.7581895010967,
						140.67239654933792,
						-0.013161160163313241,
						124.7275293124932,
						141.61952779002218,
						0.16304572853402555
					],
					"joint_state": {
						"position": [
							-2.0344,
							4.4171,
							1.1905,
							-5.2668,
							1.1834,
							-0.4202,
							0.0
						],
						"velocity": [
							-0.0108,
							0.0111,
							0.0122,
							0.0262,
							-0.0091,
							0.0311,
							0.0
						],
						"effort": [
							0.0,
							0.0,
							0.0,
							0.0,
							0.0,
							0.0,
							0.0
						]
					},
					"lift_state": "lift_down"
				}
			}
		},
		"objects": {
			"Rack": {
				"Rack_02": {
					"name": "Rack_02",
					"pose": {
						"translation": [
							133.05699157714844,
							143.09999084472656,
							0.19921104609966278
						],
						"rotation": [
							0.983835756778717,
							0.1790735274553299,
							-4.97384462505579e-08,
							9.080395102500916e-09
						]
					}
				}
			}
		},
		"relationships": {
			"L-Rack": [
				[
					"AMR_LIFT01",
					"none"
				]
			]
		}
	}
}