{
	"timestamp_0": {
		"robots": {
			"ARMLIFT": {
				"AMR_LIFT01": {
					"name": "AMR_LIFT01",
					"pose": {
						"translation": [
							139.62045288085938,
							142.43421936035156,
							0.06200237199664116
						],
						"rotation": [
							-0.009424585849046707,
							-0.003548678942024708,
							-0.9358029961585999,
							0.352379709482193
						]
					},
					"odometry": {
						"position": [
							0.5914091461991975,
							-7.865101338663199,
							-0.013371833681125857
						],
						"orientation": [
							-0.0198337563335609,
							0.0003852958528537063,
							-0.9356308571681674,
							0.35242215136334315
						],
						"linear": [
							0.00022648424783255905,
							0.0,
							0.0
						],
						"angular": [
							0.0,
							0.0,
							0.004088622517883778
						]
					},
					"aabb": [
						123.733468157546,
						140.7631681355263,
						-0.014236954222931133,
						124.71366170736806,
						141.696247130307,
						0.16288465333573818
					],
					"joint_state": {
						"position": [
							-1.4376,
							4.8601,
							1.0131,
							-5.8028,
							1.0181,
							-0.9319,
							0.0
						],
						"velocity": [
							0.0284,
							0.0136,
							-0.1404,
							0.0696,
							-0.1583,
							0.0575,
							0.0
						],
						"effort": [
							0.0,
							0.0,
							0.0,
							0.0,
							0.0,
							0.0,
							0.0
						]
					},
					"lift_state": "lift_down"
				}
			}
		},
		"objects": {
			"Rack": {
				"Rack_02": {
					"name": "Rack_02",
					"pose": {
						"translation": [
							133.05699157714844,
							143.09999084472656,
							0.19921104609966278
						],
						"rotation": [
							0.983835756778717,
							0.1790735274553299,
							-4.97384462505579e-08,
							9.080395102500916e-09
						]
					}
				}
			}
		},
		"relationships": {
			"L-Rack": [
				[
					"AMR_LIFT01",
					"none"
				]
			]
		}
	},
	"timestamp_1": {
		"robots": {
			"ARMLIFT": {
				"AMR_LIFT01": {
					"name": "AMR_LIFT01",
					"pose": {
						"translation": [
							139.62005615234375,
							142.43453979492188,
							0.06200336292386055
						],
						"rotation": [
							-0.00941894669085741,
							-0.0035535471979528666,
							-0.9356625080108643,
							0.35275280475616455
						]
					},
					"odometry": {
						"position": [
							0.5910186229871744,
							-7.864788856889975,
							-0.01336216863916052
						],
						"orientation": [
							-0.01982654623595107,
							0.00038457805725458796,
							-0.9354904257861397,
							0.3527951578842015
						],
						"linear": [
							0.0007579434313811362,
							0.0,
							0.0
						],
						"angular": [
							0.0,
							0.0,
							0.0055951620452106
						]
					},
					"aabb": [
						123.73410552995321,
						140.76268815872865,
						-0.014304073929209925,
						124.71408271023265,
						141.69607176017215,
						0.1628857618218639
					],
					"joint_state": {
						"position": [
							-1.4368,
							4.8611,
							1.0003,
							-5.795,
							1.0008,
							-0.9269,
							0.0
						],
						"velocity": [
							-0.0224,
							-0.0293,
							-0.0899,
							0.0689,
							-0.159,
							0.0521,
							0.0
						],
						"effort": [
							0.0,
							0.0,
							0.0,
							0.0,
							0.0,
							0.0,
							0.0
						]
					},
					"lift_state": "lift_down"
				}
			}
		},
		"objects": {
			"Rack": {
				"Rack_02": {
					"name": "Rack_02",
					"pose": {
						"translation": [
							133.05699157714844,
							143.09999084472656,
							0.19921104609966278
						],
						"rotation": [
							0.983835756778717,
							0.1790735274553299,
							-4.97384462505579e-08,
							9.080395102500916e-09
						]
					}
				}
			}
		},
		"relationships": {
			"L-Rack": [
				[
					"AMR_LIFT01",
					"none"
				]
			]
		}
	},
	"timestamp_2": {
		"robots": {
			"ARMLIFT": {
				"AMR_LIFT01": {
					"name": "AMR_LIFT01",
					"pose": {
						"translation": [
							139.6202392578125,
							142.4346923828125,
							0.06199996918439865
						],
						"rotation": [
							-0.00940765906125307,
							-0.0035459939390420914,
							-0.9356887340545654,
							0.35268351435661316
						]
					},
					"odometry": {
						"position": [
							0.5912040407080613,
							-7.864632603378194,
							-0.013369662228502364
						],
						"orientation": [
							-0.019815553743760508,
							0.00039136080740772135,
							-0.9355167851033589,
							0.3527258644562697
						],
						"linear": [
							9.563084313413128e-05,
							0.0,
							0.0
						],
						"angular": [
							0.0,
							0.0,
							0.005081966519355774
						]
					},
					"aabb": [
						123.73403923499266,
						140.76265314278243,
						-0.014350859773741167,
						124.71410542750272,
						141.69590861366606,
						0.16288393031611878
					],
					"joint_state": {
						"position": [
							-1.4364,
							4.8625,
							0.9736,
							-5.7826,
							0.9892,
							-0.9185,
							0.0
						],
						"velocity": [
							-0.0106,
							0.0143,
							-0.0259,
							0.0124,
							-0.0309,
							0.0118,
							0.0
						],
						"effort": [
							0.0,
							0.0,
							0.0,
							0.0,
							0.0,
							0.0,
							0.0
						]
					},
					"lift_state": "lift_down"
				}
			}
		},
		"objects": {
			"Rack": {
				"Rack_02": {
					"name": "Rack_02",
					"pose": {
						"translation": [
							133.05699157714844,
							143.09999084472656,
							0.19921104609966278
						],
						"rotation": [
							0.983835756778717,
							0.1790735274553299,
							-4.97384462505579e-08,
							9.080395102500916e-09
						]
					}
				}
			}
		},
		"relationships": {
			"L-Rack": [
				[
					"AMR_LIFT01",
					"none"
				]
			]
		}
	},
	"timestamp_3": {
		"robots": {
			"ARMLIFT": {
				"AMR_LIFT01": {
					"name": "AMR_LIFT01",
					"pose": {
						"translation": [
							139.61936950683594,
							142.435302734375,
							0.06200210377573967
						],
						"rotation": [
							-0.009419240057468414,
							-0.00354535854421556,
							-0.9358525276184082,
							0.35224828124046326
						]
					},
					"odometry": {
						"position": [
							0.5903351304126528,
							-7.864017409747419,
							-0.01334817558835844
						],
						"orientation": [
							-0.019828965417598318,
							0.00038715438724870995,
							-0.9356804518084293,
							0.35229072418319785
						],
						"linear": [
							-0.0018298679497092962,
							0.0,
							0.0
						],
						"angular": [
							0.0,
							0.0,
							0.004602784290909767
						]
					},
					"aabb": [
						123.73459448827258,
						140.76218231705084,
						-0.014294760349864448,
						124.71486545578232,
						141.69514852298101,
						0.16288473300812847
					],
					"joint_state": {
						"position": [
							-1.4351,
							4.8636,
							0.9958,
							-5.7918,
							1.0187,
							-0.932,
							0.0
						],
						"velocity": [
							0.0404,
							-0.0032,
							-0.0177,
							0.0368,
							-0.0703,
							-0.0645,
							0.0
						],
						"effort": [
							0.0,
							0.0,
							0.0,
							0.0,
							0.0,
							0.0,
							0.0
						]
					},
					"lift_state": "lift_down"
				}
			}
		},
		"objects": {
			"Rack": {
				"Rack_02": {
					"name": "Rack_02",
					"pose": {
						"translation": [
							133.05699157714844,
							143.09999084472656,
							0.19921104609966278
						],
						"rotation": [
							0.983835756778717,
							0.1790735274553299,
							-4.97384462505579e-08,
							9.080395102500916e-09
						]
					}
				}
			}
		},
		"relationships": {
			"L-Rack": [
				[
					"AMR_LIFT01",
					"none"
				]
			]
		}
	},
	"timestamp_4": {
		"robots": {
			"ARMLIFT": {
				"AMR_LIFT01": {
					"name": "AMR_LIFT01",
					"pose": {
						"translation": [
							139.618408203125,
							142.43568420410156,
							0.06200256198644638
						],
						"rotation": [
							-0.00941549800336361,
							-0.0035396055318415165,
							-0.9357607960700989,
							0.35249221324920654
						]
					},
					"odometry": {
						"position": [
							0.5893783273114055,
							-7.86363659946388,
							-0.013326368074242825
						],
						"orientation": [
							-0.019824194906904794,
							0.0003956200108163505,
							-0.935588766834337,
							0.35253440137737596
						],
						"linear": [
							-0.00027186577790416777,
							0.0,
							0.0
						],
						"angular": [
							0.0,
							0.0,
							0.0011923827696591616
						]
					},
					"aabb": [
						123.73542060153657,
						140.761862974607,
						-0.014243437372057365,
						124.71554323440103,
						141.695038882724,
						0.16288393009783453
					],
					"joint_state": {
						"position": [
							-1.435,
							4.8648,
							0.9821,
							-5.7881,
							1.0018,
							-0.9305,
							0.0
						],
						"velocity": [
							0.0045,
							0.0287,
							-0.0098,
							-0.0265,
							-0.0704,
							-0.0202,
							0.0
						],
						"effort": [
							0.0,
							0.0,
							0.0,
							0.0,
							0.0,
							0.0,
							0.0
						]
					},
					"lift_state": "lift_down"
				}
			}
		},
		"objects": {
			"Rack": {
				"Rack_02": {
					"name": "Rack_02",
					"pose": {
						"translation": [
							133.05699157714844,
							143.09999084472656,
							0.19921104609966278
						],
						"rotation": [
							0.983835756778717,
							0.1790735274553299,
							-4.97384462505579e-08,
							9.080395102500916e-09
						]
					}
				}
			}
		},
		"relationships": {
			"L-Rack": [
				[
					"AMR_LIFT01",
					"none"
				]
			]
		}
	}
}